adminaudit/admin.py
adminaudit/tests.py
adminaudit/schema.py
adminaudit/models.py
adminaudit/__init__.py
adminaudit/management/__init__.py
adminaudit/management/commands/adminaudit_email_report.py
adminaudit/management/commands/__init__.py
adminaudit/management/commands/adminaudit_report.py
adminaudit/south_migrations/0002_auto__chg_field_auditlog_username__chg_field_auditlog_representation__.py
adminaudit/south_migrations/0001_initial.py
adminaudit/south_migrations/__init__.py
adminaudit/migrations/0001_initial.py
adminaudit/migrations/__init__.py
adminaudit/templates/admin/base_site.html
adminaudit/templates/admin/adminaudit/auditlog/change_form.html
adminaudit/templates/adminaudit/report.txt
django_adminaudit-0.5.dist-info/top_level.txt
django_adminaudit-0.5.dist-info/metadata.json
django_adminaudit-0.5.dist-info/METADATA
django_adminaudit-0.5.dist-info/WHEEL
django_adminaudit-0.5.dist-info/RECORD
django_adminaudit-0.5.dist-info/DESCRIPTION.rst
