Metadata-Version: 2.0
Name: django-adminaudit
Version: 0.5
Summary: Extends Django's admin logging capabilities
Home-page: https://launchpad.net/django-adminaudit
Author: Ubuntu One Hackers
Author-email: natalia.bidart@ubuntu.com
License: LGPLv3
Platform: UNKNOWN
Classifier: Framework :: Django
Classifier: License :: OSI Approved :: GNU Library or Lesser General Public License (LGPL)
Classifier: Programming Language :: Python :: 2.7
Classifier: Topic :: Software Development :: Libraries
Classifier: Topic :: Software Development :: Libraries :: Python Modules
